{
  "project_info": {
    "project_number": "1048576292379",
    "firebase_url": "https://levelup-5066a.firebaseio.com",
    "project_id": "levelup-5066a",
    "storage_bucket": "levelup-5066a.appspot.com"
  },
  "client": [
    {
      "client_info": {
        "mobilesdk_app_id": "1:1048576292379:android:75b5a3982b127609",
        "android_client_info": {
          "package_name": "na.mo.ri.levelup"
      }
      },
      "oauth_client": [
        {
          "client_id": "1048576292379-3rs5iu2flnr107d65bp43pa94544v3f7.apps.googleusercontent.com",
          "client_type": 3
        }
      ],
      "api_key": [
        {
          "current_key": "AIzaSyDfP40pdLlKplMkCsagaGAX-Rd71cLWI5Y"
        }
      ],
      "services": {
        "analytics_service": {
          "status": 1
        },
        "appinvite_service": {
          "status": 1,
          "other_platform_oauth_client": []
        },
        "ads_service": {
          "status": 2
        }
      }
    }
  ],
  "configuration_version": "1"
}